burpsuite/__init__.py
burpsuite/client.py
burpsuite/definitions.py
burpsuite/exceptions.py
burpsuite/get_definition.py
burpsuite-0.0.1.dist-info/LICENSE
burpsuite-0.0.1.dist-info/METADATA
burpsuite-0.0.1.dist-info/WHEEL
burpsuite-0.0.1.dist-info/top_level.txt
burpsuite-0.0.1.dist-info/RECORD
