Metadata-Version: 2.1
Name: burpsuite
Version: 0.0.1
Summary: A small library for working with the Burp Suite API
Home-page: https://github.com/Julian-Nash/burpsuite
Author: Julian Nash
Author-email: julian.nash@venturidm.com
License: UNKNOWN
Platform: UNKNOWN
Classifier: Programming Language :: Python :: 3
Classifier: License :: OSI Approved :: MIT License
Requires-Dist: certifi (==2019.9.11)
Requires-Dist: chardet (==3.0.4)
Requires-Dist: idna (==2.8)
Requires-Dist: requests (==2.22.0)
Requires-Dist: urllib3 (==1.25.6)
